ajprax/__init__.py
ajprax/cache.py
ajprax/collections.py
ajprax/files.py
ajprax/hof.py
ajprax/logging.py
ajprax/prelude.py
ajprax/print.py
ajprax/require.py
ajprax/sentinel.py
ajprax/experimental/__init__.py
ajprax/experimental/subscriptions.py
ajprax-0.0.5.dist-info/METADATA
ajprax-0.0.5.dist-info/WHEEL
ajprax-0.0.5.dist-info/licenses/LICENSE
ajprax-0.0.5.dist-info/RECORD
